ghost_your_be/__init__.py
ghost_your_be/__main__.py
ghost_your_be/cli.py
ghost_your_be/comparer/api_diff.py
ghost_your_be/database/db_config.py
ghost_your_be/database/db_connector.py
ghost_your_be/generator/data_generator.py
ghost_your_be/generator/schema_loader.py
ghost_your_be/generator/vprovider.py
ghost_your_be/mock_api/api_generator.py
ghost_your_be/mock_api/mock_server.py
ghost_your_be/test/test_database.py
ghost_your_be/test/test_generators.py
ghost_your_be/test/test_mock_api.py
ghost_your_be/util/file_exporter.py
ghost_your_be/util/license.py
ghost_your_be-0.1.5.dist-info/entry_points.txt
ghost_your_be-0.1.5.dist-info/LICENSE
ghost_your_be-0.1.5.dist-info/METADATA
ghost_your_be-0.1.5.dist-info/WHEEL
ghost_your_be-0.1.5.dist-info/RECORD
