Metadata-Version: 2.3
Name: ghost-your-be
Version: 0.1.5
Summary: A powerful tool for generating mock data and APIs
License: MIT
Keywords: mock,api,data-generation,testing,frontend
Author: Ghost Your BE Team
Requires-Python: >=3.8,<4.0
Classifier: Development Status :: 4 - Beta
Classifier: Intended Audience :: Developers
Classifier: License :: OSI Approved :: MIT License
Classifier: Programming Language :: Python :: 3
Classifier: Programming Language :: Python :: 3.8
Classifier: Programming Language :: Python :: 3.9
Classifier: Programming Language :: Python :: 3.10
Classifier: Programming Language :: Python :: 3.11
Classifier: Programming Language :: Python :: 3.12
Classifier: Programming Language :: Python :: 3.13
Classifier: Topic :: Software Development :: Libraries :: Python Modules
Classifier: Topic :: Software Development :: Testing
Requires-Dist: click (>=8.1.7,<9.0.0)
Requires-Dist: deepdiff (>=6.3.0,<7.0.0)
Requires-Dist: faker (>=19.13.0,<20.0.0)
Requires-Dist: fastapi (>=0.104.0,<0.105.0)
Requires-Dist: pydantic (>=2.5.0,<3.0.0)
Requires-Dist: pymongo (>=4.6.0,<5.0.0)
Requires-Dist: pymysql (>=1.1.0,<2.0.0)
Requires-Dist: pyyaml (>=6.0.1,<7.0.0)
Requires-Dist: requests (>=2.31.0,<3.0.0)
Requires-Dist: rich (>=13.7.0,<14.0.0)
Requires-Dist: sqlalchemy (>=2.0.23,<3.0.0)
Requires-Dist: uvicorn (>=0.24.0,<0.25.0)
Project-URL: Documentation, https://ghost-your-be.readthedocs.io
Project-URL: Repository, https://github.com/yourusername/ghost-your-be
